wiki/__init__.py
wikiguide-0.0.1.dist-info/LICENSE
wikiguide-0.0.1.dist-info/METADATA
wikiguide-0.0.1.dist-info/WHEEL
wikiguide-0.0.1.dist-info/top_level.txt
wikiguide-0.0.1.dist-info/RECORD
