Metadata-Version: 2.1
Name: wikiguide
Version: 0.0.1
Summary: Wikipedia API bindings for Python
Home-page: https://github.com/ocidenttal/wiki
Author: Mauro Torres
Author-email: mauroodesenvolvedor@gmail.com
License: UNKNOWN
Project-URL: Bug Tracker, https://github.com/ocidenttal/wiki/issues
Platform: UNKNOWN
Classifier: Programming Language :: Python :: 3
Classifier: License :: OSI Approved :: MIT License
Classifier: Operating System :: OS Independent
Requires-Python: >=3.6
License-File: LICENSE
